animtoreal/__init__.py
animtoreal/main.py
animtoreal/prompts.py
animtoreal-2025.12.21143241.dist-info/METADATA
animtoreal-2025.12.21143241.dist-info/WHEEL
animtoreal-2025.12.21143241.dist-info/top_level.txt
animtoreal-2025.12.21143241.dist-info/RECORD
