Metadata-Version: 2.4
Name: animtoreal
Version: 2025.12.21143241
Summary: This new package enables users to input a description or details about an animated character and receive a structured summary or step-by-step plan to bring that character into the real world, such as
Author-email: animtoreal <hi@eugene.plus>
License: MIT
Project-URL: Homepage, https://github.com/chigwell/animtoreal
Requires-Python: >=3.9
Requires-Dist: langchain-llm7>=0.0.0
Requires-Dist: llmatch-messages>=0.0.0
Requires-Dist: langchain-core>=0.3.0
